cfmtoolbox/__init__.py
cfmtoolbox/__main__.py
cfmtoolbox/models.py
cfmtoolbox/plugins/__init__.py
cfmtoolbox/plugins/big_m.py
cfmtoolbox/plugins/conversion.py
cfmtoolbox/plugins/debugging.py
cfmtoolbox/plugins/featureide_import.py
cfmtoolbox/plugins/json_export.py
cfmtoolbox/plugins/json_import.py
cfmtoolbox/plugins/one_wise_sampling.py
cfmtoolbox/plugins/random_sampling.py
cfmtoolbox/plugins/uvl_export.py
cfmtoolbox/plugins/uvl_import.py
cfmtoolbox/py.typed
cfmtoolbox/toolbox.py
cfmtoolbox-0.5.0.dist-info/LICENSE
cfmtoolbox-0.5.0.dist-info/METADATA
cfmtoolbox-0.5.0.dist-info/WHEEL
cfmtoolbox-0.5.0.dist-info/entry_points.txt
cfmtoolbox-0.5.0.dist-info/RECORD
