Metadata-Version: 2.3
Name: cfmtoolbox
Version: 0.5.0
Summary: A plugin-based toolbox for working with cardinality-based feature models
License: MIT
Author: Jonathan Ehwald
Author-email: github@ehwald.info
Requires-Python: >=3.11,<4.0
Classifier: Intended Audience :: Developers
Classifier: License :: OSI Approved :: MIT License
Classifier: Operating System :: OS Independent
Classifier: Programming Language :: Python
Classifier: Programming Language :: Python :: 3
Classifier: Programming Language :: Python :: 3.11
Classifier: Programming Language :: Python :: 3.12
Classifier: Programming Language :: Python :: 3.13
Requires-Dist: typer (>=0.12.3,<1.0.0)
Requires-Dist: uvlparser (>=2.0.1,<3.0.0)
Project-URL: Documentation, https://kit-tva.github.io/cfmtoolbox/
Project-URL: Homepage, https://github.com/KIT-TVA/cfmtoolbox/
Project-URL: Repository, https://github.com/KIT-TVA/cfmtoolbox/
